design.sv
//// Code your design here
module debounce(input ip_btn, clk, output out);
  reg mid_state1, mid_state2;
  
  assign out = mid_state1 && (!mid_state2);
  
  always @(posedge clk)
    begin
      mid_state1 <= ip_btn;
      mid_state2 <= mid_state1;
    end
  
endmodule

module reset_load(input ip_btn, clk, master_reset, output reset, load);
  wire sync_ip;
  reg [1:0] state;
  parameter reset_state = 2'b00, reset_mid = 2'b01, load_mid = 2'b10, load_state = 2'b11;
  
  debounce d0(ip_btn, clk, sync_ip);
  assign reset = !(state[0] || state[1]);
  assign load = state[0] && state[1];
  
  always @(posedge clk, posedge master_reset)
    begin
      if(master_reset)
        state <= 2'b0;
      else
        case(state)
          reset_state: 	if(sync_ip)
            				state <= load_state;
            			else
                          	state <= reset_mid;
          reset_mid: 	if(sync_ip)
            				state <= load_state;
          				else
                          	state <= reset_mid;
          load_mid: 	if(sync_ip)
            				state <= reset_state;
          				else
                          	state <= load_mid;
          load_state: 	if(sync_ip)
            				state <= reset_state;
          				else
                          	state <= load_mid;
          default:		state <= reset_state;
        endcase
    end
  
endmodule

module start_stop(input ip_btn, clk, master_reset, output start, stop);
  wire sync_ip;
  reg state;
  parameter start_state = 1'b1, stop_state = 1'b0;
  
  debounce d1(ip_btn, clk, sync_ip);
  assign stop = !(state);
  assign start = state;
  
  always @(posedge clk, posedge master_reset)
    begin
      if(master_reset)
        state <= stop_state;
      else
        case(state)
          stop_state: 	if(sync_ip)
            				state <= start_state;
          				else
                          	state <= stop_state;
          start_state: 	if(sync_ip)
            				state <= stop_state;
          				else
                          	state <= start_state;
          default: 		state<= stop_state;
        endcase
    end
  
endmodule

module mod_n_counter(input clk, input [3:0] load_val, input reset, load, count_enable, up_down, input [3:0] mod_n, output reg [3:0] Q, output reg C_out);
  
  always @(posedge clk, posedge reset, posedge load)
    if(reset)
      begin
        Q <= 4'b0;
        C_out <= 1'b0;
      end
    else
      if(load)
        begin
          Q <= load_val;
          C_out <= 1'b0;
        end
  	  else
        if(count_enable)
          if(up_down)
            if(Q == 4'b0)
            	begin
                	Q <= mod_n - 1;
                    C_out <= 1'b1;
                end
          	else
                begin
                    Q <= Q - 1;
                    C_out <= 1'b0;
                end
          else
            if(Q == mod_n - 1)
            	begin
                   	Q <= 4'b0;
            		C_out <= 1;
                end
          	else
                begin
                    Q <= Q + 1;
                    C_out <= 1'b0;
                end
  		else
          begin
           	Q <= Q;
  			C_out <= C_out;
          end
  
endmodule
            
module freq_divider(input clk, reset, stop, output reg div_clk);
  reg [31:0] counter;
  integer n_freq = 5_00_000;			// change the frequency depending upon the boards frequency
  
  always @(posedge clk, posedge reset)
    if(reset)
      begin
      	div_clk <= 1'b0;
        counter <= 32'b0;
      end
  	else
      if(stop)
        begin
        	div_clk <= div_clk;
          	counter <= counter;
        end
  	  else
        if(counter == n_freq)
          begin
          	div_clk <= ~div_clk;
            counter <= 32'b0;
          end
        else
          begin
          	counter <= counter + 1;
          	div_clk <= div_clk;
          end
          
endmodule
      
module stopwatch(input master_reset, button_rl, button_ss, up_down, clk, input [15:0] load_val, output [3:0] activate_anode, output [6:0] LED_out);
  wire reset, load, start, stop;
  wire div_clk;
  wire carry_clk0, carry_clk1, carry_clk2, carry_clk3;
  parameter [3:0] binary_10 = 4'b1010;
  parameter [3:0] binary_6 = 4'b0110;
  wire count_enable;
  wire [15:0] Q;
  
  reset_load r0(button_rl, clk, master_reset, reset, load);
  start_stop s0(button_ss, clk, master_reset, start, stop);
  
  assign count_enable = start;
  
  freq_divider f0(clk, reset, stop, div_clk);
  
  mod_n_counter counter0(div_clk, load_val[3:0], reset, load, count_enable, up_down, binary_10, Q[3:0], carry_clk0);
  mod_n_counter counter1(carry_clk0, load_val[7:4], reset, load, count_enable,up_down, binary_10, Q[7:4], carry_clk1);
  mod_n_counter counter2(carry_clk1, load_val[11:8], reset, load, count_enable,up_down, binary_10, Q[11:8], carry_clk2);
  mod_n_counter counter3(carry_clk2, load_val[15:12], reset, load, count_enable,up_down, binary_6, Q[15:12], carry_clk3);
  
  seven_segment_display ssd0(clk, master_reset, Q, activate_anode, LED_out);
  
endmodule
  
module seven_segment_display(input clk, master_reset, input [15:0] Q, output reg [3:0] Anode_Activate, output reg [6:0] LED_out);
  parameter [5:0] n = 19;			// can change the refresh rate here
  reg [n:0] refresh_counter; 
    reg [3:0] LED_BCD;
    wire [1:0] LED_activating_counter; 
  always @(posedge clk, posedge master_reset)
    begin 
      if(master_reset)
            refresh_counter <= 0;
        else
            refresh_counter <= refresh_counter + 1;
    end 
  assign LED_activating_counter = refresh_counter[n:n-1];
    
  always @(*)
    begin
        case(LED_activating_counter)
        2'b00: begin
            Anode_Activate = 4'b0111;  // 7
            // activate LED1 and Deactivate LED2, LED3, LED4
            LED_BCD = Q[3:0];
            // the first hex-digit of the 16-bit number
             end
        2'b01: begin
            Anode_Activate = 4'b1011; //11 b
            // activate LED2 and Deactivate LED1, LED3, LED4
          LED_BCD = Q[7:4];
            // the second hex-digit of the 16-bit number
                end
        2'b10: begin
            Anode_Activate = 4'b1101; //13 d
            // activate LED3 and Deactivate LED2, LED1, LED4
          LED_BCD = Q[11:8];
             // the third hex-digit of the 16-bit number
              end
        2'b11: begin
            Anode_Activate = 4'b1110; // e
            // activate LED4 and Deactivate LED2, LED3, LED1
          LED_BCD = Q[15:12];
             // the fourth hex-digit of the 16-bit number 
               end   
        default:begin
             Anode_Activate = 4'b0111; 
            // activate LED1 and Deactivate LED2, LED3, LED4
            LED_BCD = Q[3:0];
            // the first hex-digit of the 16-bit number
            end
        endcase
    end
    always @(*)
    begin
     case(LED_BCD)
     4'b0000: LED_out = 7'b0000001; // "0"  //h01
     4'b0001: LED_out = 7'b1001111; // "1" 	//h4F
     4'b0010: LED_out = 7'b0010010; // "2" 	//h12
     4'b0011: LED_out = 7'b0000110; // "3" 	//h06
     4'b0100: LED_out = 7'b1001100; // "4" 	//h4C
     4'b0101: LED_out = 7'b0100100; // "5" 	//h24
     4'b0110: LED_out = 7'b0100000; // "6" 	//h20
     4'b0111: LED_out = 7'b0001111; // "7" 	//h0F
     4'b1000: LED_out = 7'b0000000; // "8"  //h00
     4'b1001: LED_out = 7'b0000100; // "9" 	//h04
     default: LED_out = 7'b0000001; // "0"	//h01
     endcase
    end
endmodule

testbench.sv
// Code your testbench here
// or browse Examples

/* De-Comment this module to test reset-load state transitions
module t_state_trans_check;
  reg clk, ip_btn, reset_b;
  wire reset, load;
  reset_load MUT(ip_btn, clk, reset_b, reset, load);
  
  always #1 clk = ~ clk;
    
  initial
    begin
    clk = 0; reset_b = 0; ip_btn = 0;
    $dumpfile("dump.vcd");
    $dumpvars(0,t_state_trans_check);
    $monitor($time, " clk = %2d, input = %b, reset_button = %b, reset_out = %b, load_out = %b, state = %2b", clk, ip_btn, reset_b, reset, load, MUT.state);
    end
  
    
  initial fork
    #3 reset_b = 1;
    #6 reset_b = 0;
    
    #9  ip_btn = 1;			// load
    #11 ip_btn = 0;
    #15 ip_btn = 1;			// reset
    #18 ip_btn = 0;
    #26 ip_btn = 1;			// load
    #30 ip_btn = 0;
    #35 ip_btn = 1;			// reset
    #40 $finish;  
  join
endmodule
*/

/* De-comment this block to check start-stop
module t_state_trans_check;
  wire start, stop;
  reg ip_btn, clk, reset_b;
  start_stop MUT(ip_btn, clk, reset_b, start, stop);
  
  always #1 clk = ~clk;
  
  initial fork
    clk = 0; reset_b = 0; ip_btn = 0;
    $dumpfile("dump.vcd");
    $dumpvars(0,t_state_trans_check);
    $monitor($time, " clk = %2d, input = %b, reset_button = %b, stop = %b, start = %b, state = %b", clk, ip_btn, reset_b, stop, start, MUT.state);
    
    #3 reset_b = 1;
    #6 reset_b = 0;
    
    #8  ip_btn = 1;		// start
    #11 ip_btn = 0;
    #15 ip_btn = 1;		// stop
    #19 ip_btn = 0; 
    #25 ip_btn = 1;		// start
    #30 ip_btn = 0;
    #31 $finish;
  join
  
endmodule
*/    

/* De-comment this module to check counter
module t_counter;
  wire [3:0] Q;
  wire C_out;
  reg clk, reset, load,count_enable, up_down;
  reg [3:0] load_val, mod_n;
  mod_n_counter MUT(clk, load_val, reset, load, count_enable, up_down, mod_n, Q, C_out);
  
  always #2 clk = ~clk;
  
  always @(reset, load, load_val, count_enable, up_down)
    $display("reset = %b, load = %b, load_val = %4b, count_enable = %b, up_down = %b", reset, load, load_val, count_enable, up_down);  
  
  initial fork
    clk = 0; load_val = 7; reset = 0; load = 0; count_enable = 0; up_down = 0;mod_n = 10;
    $dumpvars(0,t_counter);
    $dumpfile("dump.vcd");
    $monitor($time, " clk = %2b   Q = %d   C_out = %b", clk, Q, C_out);
    
    #1  reset = 1;
    #4  reset = 0;
    #52 reset = 1;
    #55 reset = 0;
    
    #4  count_enable = 1;
    #40 count_enable = 0;
    #53 count_enable = 1;
    #77 count_enable = 0;
    #82 count_enable = 1;
    
    #22 load = 1; 
    #24 load = 0;
    #63 load = 1; 
    #63 load_val = 4;
    #67 load = 0;
    
    #20 up_down = 1;
    #65 up_down = 0;
    #84 up_down = 1;
    #102 up_down = 0;
    
    #190 $finish;
  join
  
endmodule
*/

/* De-comment this module to check frequency divider
module t_freq_divider;
  wire div_clk;
  reg clk, reset, stop;
  freq_divider MUT(clk, reset, stop, div_clk);
  
  always #1 clk = ~clk;
  
  initial fork
    $dumpvars(0,t_freq_divider);
    $dumpfile("dump.vcd");    
    //$monitor($time, " clk = %b  reset = %b  stop = %b  div_clk = %b  counter = %1d", clk, reset, stop, div_clk, MUT.counter);
    
    clk = 0; reset = 0; stop = 0;
    
    #2 reset = 1;
    #6 reset = 0;
    
    #82 stop = 1;
    #148 stop = 0;
    #600 stop = 1;
    
    #10000 $finish;
  join
  
endmodule
*/

// De-comment for checking stopwatch
module t_stopwatch;
  //wire [15:0] Q;
  wire [3:0] activate_anode;
  wire [6:0] LED_out;
  reg master_reset, button_rl, button_ss, up_down,clk;
  reg [15:0] load_val;
  stopwatch MUT(master_reset, button_rl, button_ss, up_down, clk, load_val, activate_anode, LED_out);
  
  always #1 clk = ~clk;
  
  initial 
    begin
      $dumpfile("stopwatch.vcd");
      $dumpvars(0, t_stopwatch);
      $monitor($time, " button_ss = %b button_rl = %b up_down = %b Q = %h activate_anode = %h", button_ss, button_rl, up_down, MUT.Q, activate_anode);
      clk = 0; master_reset = 0; button_rl = 0; button_ss = 0; up_down = 1; load_val = 0;
    end
      
  
  initial fork
    #1 master_reset = 1;
    #4 master_reset = 0;
    
    #7 button_ss = 1;			// start
    #9 button_ss = 0;
    #1132 button_ss = 1;		// stops the stopwatch
    #1150 button_ss = 0;
    #1300 button_ss = 1;		// starts the stopwatch
    #1308 button_ss = 0;
    
    #2500 load_val = 16'h5875;
    #8000 load_val = 16'h1567;
    
    #2503 button_rl = 1;		// load
    #2510 button_rl = 0;
    #7000 button_rl = 1;		// reset
    #7008 button_rl = 0;
    #8000 button_rl = 1;		// load
    #8100 button_rl = 0; 	
    
    #1550 up_down = 0;
    #5000 up_down = 1;
    
    #11000 $finish;
  join
  
endmodule    


/* De-comment to check seven-segment display
module t_7_segment_display;
  wire [6:0] LED_out;
  wire [3:0] Anode_Activate;
  reg clk, master_reset;
  reg [15:0] Q;
  seven_segment_display MUT(clk, master_reset, Q, Anode_Activate, LED_out);
  
  always #1 clk = ~clk;
  
  initial 
    begin
      $dumpfile("dump.vcd");
      $dumpvars(0,t_7_segment_display);
      $monitor($time, " Q = %b  Active anode = %b  LED_out = %h", Q, Anode_Activate, LED_out);
      clk = 1; Q = 0; master_reset = 1;
    end
  
  initial fork
    #6 master_reset = 0;
    #1000 Q = 16'h5432;
    #6000 Q = 16'h2689;
    #11000 Q = 16'h0741;
    #18000 $finish;
  join
  
endmodule
*/

stopwatch.vcd
$date
	Tue Aug 25 19:02:06 2020
$end
$version
	Icarus Verilog
$end
$timescale
	1s
$end
$scope module t_stopwatch $end
$var wire 7 ! LED_out [6:0] $end
$var wire 4 " activate_anode [3:0] $end
$var reg 1 # button_rl $end
$var reg 1 $ button_ss $end
$var reg 1 % clk $end
$var reg 16 & load_val [15:0] $end
$var reg 1 ' master_reset $end
$var reg 1 ( up_down $end
$scope module MUT $end
$var wire 7 ) LED_out [6:0] $end
$var wire 16 * Q [15:0] $end
$var wire 4 + activate_anode [3:0] $end
$var wire 1 , button_rl $end
$var wire 1 - button_ss $end
$var wire 1 . carry_clk0 $end
$var wire 1 / carry_clk1 $end
$var wire 1 0 carry_clk2 $end
$var wire 1 1 carry_clk3 $end
$var wire 1 2 clk $end
$var wire 1 3 count_enable $end
$var wire 1 4 div_clk $end
$var wire 1 5 load $end
$var wire 16 6 load_val [15:0] $end
$var wire 1 7 master_reset $end
$var wire 1 8 reset $end
$var wire 1 9 start $end
$var wire 1 : stop $end
$var wire 1 ; up_down $end
$scope module r0 $end
$var wire 1 2 clk $end
$var wire 1 , ip_btn $end
$var wire 1 5 load $end
$var wire 1 7 master_reset $end
$var wire 1 8 reset $end
$var wire 1 < sync_ip $end
$var reg 2 = state [1:0] $end
$scope module d0 $end
$var wire 1 2 clk $end
$var wire 1 , ip_btn $end
$var wire 1 < out $end
$var reg 1 > mid_state1 $end
$var reg 1 ? mid_state2 $end
$upscope $end
$upscope $end
$scope module s0 $end
$var wire 1 2 clk $end
$var wire 1 - ip_btn $end
$var wire 1 7 master_reset $end
$var wire 1 9 start $end
$var wire 1 : stop $end
$var wire 1 @ sync_ip $end
$var reg 1 A state $end
$scope module d1 $end
$var wire 1 2 clk $end
$var wire 1 - ip_btn $end
$var wire 1 @ out $end
$var reg 1 B mid_state1 $end
$var reg 1 C mid_state2 $end
$upscope $end
$upscope $end
$scope module f0 $end
$var wire 1 2 clk $end
$var wire 1 8 reset $end
$var wire 1 : stop $end
$var reg 32 D counter [31:0] $end
$var reg 1 E div_clk $end
$var integer 32 F n_freq [31:0] $end
$upscope $end
$scope module counter0 $end
$var wire 1 4 clk $end
$var wire 1 3 count_enable $end
$var wire 1 5 load $end
$var wire 4 G load_val [3:0] $end
$var wire 4 H mod_n [3:0] $end
$var wire 1 8 reset $end
$var wire 1 ; up_down $end
$var reg 1 I C_out $end
$var reg 4 J Q [3:0] $end
$upscope $end
$scope module counter1 $end
$var wire 1 . clk $end
$var wire 1 3 count_enable $end
$var wire 1 5 load $end
$var wire 4 K load_val [3:0] $end
$var wire 4 L mod_n [3:0] $end
$var wire 1 8 reset $end
$var wire 1 ; up_down $end
$var reg 1 M C_out $end
$var reg 4 N Q [3:0] $end
$upscope $end
$scope module counter2 $end
$var wire 1 / clk $end
$var wire 1 3 count_enable $end
$var wire 1 5 load $end
$var wire 4 O load_val [3:0] $end
$var wire 4 P mod_n [3:0] $end
$var wire 1 8 reset $end
$var wire 1 ; up_down $end
$var reg 1 Q C_out $end
$var reg 4 R Q [3:0] $end
$upscope $end
$scope module counter3 $end
$var wire 1 0 clk $end
$var wire 1 3 count_enable $end
$var wire 1 5 load $end
$var wire 4 S load_val [3:0] $end
$var wire 4 T mod_n [3:0] $end
$var wire 1 8 reset $end
$var wire 1 ; up_down $end
$var reg 1 U C_out $end
$var reg 4 V Q [3:0] $end
$upscope $end
$scope module ssd0 $end
$var wire 2 W LED_activating_counter [1:0] $end
$var wire 16 X Q [15:0] $end
$var wire 1 2 clk $end
$var wire 1 7 master_reset $end
$var reg 4 Y Anode_Activate [3:0] $end
$var reg 4 Z LED_BCD [3:0] $end
$var reg 7 [ LED_out [6:0] $end
$var reg 20 \ refresh_counter [19:0] $end
$upscope $end
$upscope $end
$upscope $end
$enddefinitions $end
#0
$dumpvars
bx \
bx [
bx Z
b111 Y
bx X
bx W
bx V
xU
b110 T
b0 S
bx R
xQ
b1010 P
b0 O
bx N
xM
b1010 L
b0 K
bx J
xI
b1010 H
b0 G
b1111010000100100000 F
xE
bx D
xC
xB
xA
x@
x?
x>
bx =
x<
1;
x:
x9
x8
07
b0 6
x5
x4
x3
02
x1
x0
x/
x.
0-
0,
b111 +
bx *
bx )
1(
0'
b0 &
0%
0$
0#
b111 "
bx !
$end
#1
b1 [
b1 !
b1 )
b0 Z
0U
01
b0 V
0Q
00
b0 R
0M
0/
b0 N
0I
0.
b0 J
b0 *
b0 X
b0 D
0E
04
18
05
b0 W
0<
0@
b0 =
0A
1:
09
03
b0 \
0>
0B
1'
17
1%
12
#2
0%
02
#3
0C
0?
1%
12
#4
0%
02
0'
07
#5
08
b1 =
b1 \
1%
12
#6
0%
02
#7
1@
b10 \
1B
1%
12
1$
1-
#8
0%
02
#9
0@
1A
0:
19
13
b11 \
1C
0B
1%
12
0$
0-
#10
0%
02
#11
b100 \
b1 D
0C
1%
12
#12
0%
02
#13
b101 \
b10 D
1%
12
#14
0%
02
#15
b110 \
b11 D
1%
12
#16
0%
02
#17
b111 \
b100 D
1%
12
#18
0%
02
#19
b1000 \
b101 D
1%
12
#20
0%
02
#21
b1001 \
b110 D
1%
12
#22
0%
02
#23
b1010 \
b111 D
1%
12
#24
0%
02
#25
b1011 \
b1000 D
1%
12
#26
0%
02
#27
b1100 \
b1001 D
1%
12
#28
0%
02
#29
b1101 \
b1010 D
1%
12
#30
0%
02
#31
b1110 \
b1011 D
1%
12
#32
0%
02
#33
b1111 \
b1100 D
1%
12
#34
0%
02
#35
b10000 \
b1101 D
1%
12
#36
0%
02
#37
b10001 \
b1110 D
1%
12
#38
0%
02
#39
b10010 \
b1111 D
1%
12
#40
0%
02
#41
b10011 \
b10000 D
1%
12
#42
0%
02
#43
b10100 \
b10001 D
1%
12
#44
0%
02
#45
b10101 \
b10010 D
1%
12
#46
0%
02
#47
b10110 \
b10011 D
1%
12
#48
0%
02
#49
b10111 \
b10100 D
1%
12
#50
0%
02
#51
b11000 \
b10101 D
1%
12
#52
0%
02
#53
b11001 \
b10110 D
1%
12
#54
0%
02
#55
b11010 \
b10111 D
1%
12
#56
0%
02
#57
b11011 \
b11000 D
1%
12
#58
0%
02
#59
b11100 \
b11001 D
1%
12
#60
0%
02
#61
b11101 \
b11010 D
1%
12
#62
0%
02
#63
b11110 \
b11011 D
1%
12
#64
0%
02
#65
b11111 \
b11100 D
1%
12
#66
0%
02
#67
b100000 \
b11101 D
1%
12
#68
0%
02
#69
b100001 \
b11110 D
1%
12
#70
0%
02
#71
b100010 \
b11111 D
1%
12
#72
0%
02
#73
b100011 \
b100000 D
1%
12
#74
0%
02
#75
b100100 \
b100001 D
1%
12
#76
0%
02
#77
b100101 \
b100010 D
1%
12
#78
0%
02
#79
b100110 \
b100011 D
1%
12
#80
0%
02
#81
b100111 \
b100100 D
1%
12
#82
0%
02
#83
b101000 \
b100101 D
1%
12
#84
0%
02
#85
b101001 \
b100110 D
1%
12
#86
0%
02
#87
b101010 \
b100111 D
1%
12
#88
0%
02
#89
b101011 \
b101000 D
1%
12
#90
0%
02
#91
b101100 \
b101001 D
1%
12
#92
0%
02
#93
b101101 \
b101010 D
1%
12
#94
0%
02
#95
b101110 \
b101011 D
1%
12
#96
0%
02
#97
b101111 \
b101100 D
1%
12
#98
0%
02
#99
b110000 \
b101101 D
1%
12
#100
0%
02
#101
b110001 \
b101110 D
1%
12
#102
0%
02
#103
b110010 \
b101111 D
1%
12
#104
0%
02
#105
b110011 \
b110000 D
1%
12
#106
0%
02
#107
b110100 \
b110001 D
1%
12
#108
0%
02
#109
b110101 \
b110010 D
1%
12
#110
0%
02
#111
b110110 \
b110011 D
1%
12
#112
0%
02
#113
b110111 \
b110100 D
1%
12
#114
0%
02
#115
b111000 \
b110101 D
1%
12
#116
0%
02
#117
b111001 \
b110110 D
1%
12
#118
0%
02
#119
b111010 \
b110111 D
1%
12
#120
0%
02
#121
b111011 \
b111000 D
1%
12
#122
0%
02
#123
b111100 \
b111001 D
1%
12
#124
0%
02
#125
b111101 \
b111010 D
1%
12
#126
0%
02
#127
b111110 \
b111011 D
1%
12
#128
0%
02
#129
b111111 \
b111100 D
1%
12
#130
0%
02
#131
b1000000 \
b111101 D
1%
12
#132
0%
02
#133
b1000001 \
b111110 D
1%
12
#134
0%
02
#135
b1000010 \
b111111 D
1%
12
#136
0%
02
#137
b1000011 \
b1000000 D
1%
12
#138
0%
02
#139
b1000100 \
b1000001 D
1%
12
#140
0%
02
#141
b1000101 \
b1000010 D
1%
12
#142
0%
02
#143
b1000110 \
b1000011 D
1%
12
#144
0%
02
#145
b1000111 \
b1000100 D
1%
12
#146
0%
02
#147
b1001000 \
b1000101 D
1%
12
#148
0%
02
#149
b1001001 \
b1000110 D
1%
12
#150
0%
02
#151
b1001010 \
b1000111 D
1%
12
#152
0%
02
#153
b1001011 \
b1001000 D
1%
12
#154
0%
02
#155
b1001100 \
b1001001 D
1%
12
#156
0%
02
#157
b1001101 \
b1001010 D
1%
12
#158
0%
02
#159
b1001110 \
b1001011 D
1%
12
#160
0%
02
#161
b1001111 \
b1001100 D
1%
12
#162
0%
02
#163
b1010000 \
b1001101 D
1%
12
#164
0%
02
#165
b1010001 \
b1001110 D
1%
12
#166
0%
02
#167
b1010010 \
b1001111 D
1%
12
#168
0%
02
#169
b1010011 \
b1010000 D
1%
12
#170
0%
02
#171
b1010100 \
b1010001 D
1%
12
#172
0%
02
#173
b1010101 \
b1010010 D
1%
12
#174
0%
02
#175
b1010110 \
b1010011 D
1%
12
#176
0%
02
#177
b1010111 \
b1010100 D
1%
12
#178
0%
02
#179
b1011000 \
b1010101 D
1%
12
#180
0%
02
#181
b1011001 \
b1010110 D
1%
12
#182
0%
02
#183
b1011010 \
b1010111 D
1%
12
#184
0%
02
#185
b1011011 \
b1011000 D
1%
12
#186
0%
02
#187
b1011100 \
b1011001 D
1%
12
#188
0%
02
#189
b1011101 \
b1011010 D
1%
12
#190
0%
02
#191
b1011110 \
b1011011 D
1%
12
#192
0%
02
#193
b1011111 \
b1011100 D
1%
12
#194
0%
02
#195
b1100000 \
b1011101 D
1%
12
#196
0%
02
#197
b1100001 \
b1011110 D
1%
12
#198
0%
02
#199
b1100010 \
b1011111 D
1%
12
#200
0%
02
#201
b1100011 \
b1100000 D
1%
12
#202
0%
02
#203
b1100100 \
b1100001 D
1%
12
#204
0%
02
#205
b1100101 \
b1100010 D
1%
12
#206
0%
02
#207
b1100110 \
b1100011 D
1%
12
#208
0%
02
#209
b1100111 \
b1100100 D
1%
12
#210
0%
02
#211
b1101000 \
b1100101 D
1%
12
#212
0%
02
#213
b1101001 \
b1100110 D
1%
12
#214
0%
02
#215
b1101010 \
b1100111 D
1%
12
#216
0%
02
#217
b1101011 \
b1101000 D
1%
12
#218
0%
02
#219
b1101100 \
b1101001 D
1%
12
#220
0%
02
#221
b1101101 \
b1101010 D
1%
12
#222
0%
02
#223
b1101110 \
b1101011 D
1%
12
#224
0%
02
#225
b1101111 \
b1101100 D
1%
12
#226
0%
02
#227
b1110000 \
b1101101 D
1%
12
#228
0%
02
#229
b1110001 \
b1101110 D
1%
12
#230
0%
02
#231
b1110010 \
b1101111 D
1%
12
#232
0%
02
#233
b1110011 \
b1110000 D
1%
12
#234
0%
02
#235
b1110100 \
b1110001 D
1%
12
#236
0%
02
#237
b1110101 \
b1110010 D
1%
12
#238
0%
02
#239
b1110110 \
b1110011 D
1%
12
#240
0%
02
#241
b1110111 \
b1110100 D
1%
12
#242
0%
02
#243
b1111000 \
b1110101 D
1%
12
#244
0%
02
#245
b1111001 \
b1110110 D
1%
12
#246
0%
02
#247
b1111010 \
b1110111 D
1%
12
#248
0%
02
#249
b1111011 \
b1111000 D
1%
12
#250
0%
02
#251
b1111100 \
b1111001 D
1%
12
#252
0%
02
#253
b1111101 \
b1111010 D
1%
12
#254
0%
02
#255
b1111110 \
b1111011 D
1%
12
#256
0%
02
#257
b1111111 \
b1111100 D
1%
12
#258
0%
02
#259
b10000000 \
b1111101 D
1%
12
#260
0%
02
#261
b10000001 \
b1111110 D
1%
12
#262
0%
02
#263
b10000010 \
b1111111 D
1%
12
#264
0%
02
#265
b10000011 \
b10000000 D
1%
12
#266
0%
02
#267
b10000100 \
b10000001 D
1%
12
#268
0%
02
#269
b10000101 \
b10000010 D
1%
12
#270
0%
02
#271
b10000110 \
b10000011 D
1%
12
#272
0%
02
#273
b10000111 \
b10000100 D
1%
12
#274
0%
02
#275
b10001000 \
b10000101 D
1%
12
#276
0%
02
#277
b10001001 \
b10000110 D
1%
12
#278
0%
02
#279
b10001010 \
b10000111 D
1%
12
#280
0%
02
#281
b10001011 \
b10001000 D
1%
12
#282
0%
02
#283
b10001100 \
b10001001 D
1%
12
#284
0%
02
#285
b10001101 \
b10001010 D
1%
12
#286
0%
02
#287
b10001110 \
b10001011 D
1%
12
#288
0%
02
#289
b10001111 \
b10001100 D
1%
12
#290
0%
02
#291
b10010000 \
b10001101 D
1%
12
#292
0%
02
#293
b10010001 \
b10001110 D
1%
12
#294
0%
02
#295
b10010010 \
b10001111 D
1%
12
#296
0%
02
#297
b10010011 \
b10010000 D
1%
12
#298
0%
02
#299
b10010100 \
b10010001 D
1%
12
#300
0%
02
#301
b10010101 \
b10010010 D
1%
12
#302
0%
02
#303
b10010110 \
b10010011 D
1%
12
#304
0%
02
#305
b10010111 \
b10010100 D
1%
12
#306
0%
02
#307
b10011000 \
b10010101 D
1%
12
#308
0%
02
#309
b10011001 \
b10010110 D
1%
12
#310
0%
02
#311
b10011010 \
b10010111 D
1%
12
#312
0%
02
#313
b10011011 \
b10011000 D
1%
12
#314
0%
02
#315
b10011100 \
b10011001 D
1%
12
#316
0%
02
#317
b10011101 \
b10011010 D
1%
12
#318
0%
02
#319
b10011110 \
b10011011 D
1%
12
#320
0%
02
#321
b10011111 \
b10011100 D
1%
12
#322
0%
02
#323
b10100000 \
b10011101 D
1%
12
#324
0%
02
#325
b10100001 \
b10011110 D
1%
12
#326
0%
02
#327
b10100010 \
b10011111 D
1%
12
#328
0%
02
#329
b10100011 \
b10100000 D
1%
12
#330
0%
02
#331
b10100100 \
b10100001 D
1%
12
#332
0%
02
#333
b10100101 \
b10100010 D
1%
12
#334
0%
02
#335
b10100110 \
b10100011 D
1%
12
#336
0%
02
#337
b10100111 \
b10100100 D
1%
12
#338
0%
02
#339
b10101000 \
b10100101 D
1%
12
#340
0%
02
#341
b10101001 \
b10100110 D
1%
12
#342
0%
02
#343
b10101010 \
b10100111 D
1%
12
#344
0%
02
#345
b10101011 \
b10101000 D
1%
12
#346
0%
02
#347
b10101100 \
b10101001 D
1%
12
#348
0%
02
#349
b10101101 \
b10101010 D
1%
12
#350
0%
02
#351
b10101110 \
b10101011 D
1%
12
#352
0%
02
#353
b10101111 \
b10101100 D
1%
12
#354
0%
02
#355
b10110000 \
b10101101 D
1%
12
#356
0%
02
#357
b10110001 \
b10101110 D
1%
12
#358
0%
02
#359
b10110010 \
b10101111 D
1%
12
#360
0%
02
#361
b10110011 \
b10110000 D
1%
12
#362
0%
02
#363
b10110100 \
b10110001 D
1%
12
#364
0%
02
#365
b10110101 \
b10110010 D
1%
12
#366
0%
02
#367
b10110110 \
b10110011 D
1%
12
#368
0%
02
#369
b10110111 \
b10110100 D
1%
12
#370
0%
02
#371
b10111000 \
b10110101 D
1%
12
#372
0%
02
#373
b10111001 \
b10110110 D
1%
12
#374
0%
02
#375
b10111010 \
b10110111 D
1%
12
#376
0%
02
#377
b10111011 \
b10111000 D
1%
12
#378
0%
02
#379
b10111100 \
b10111001 D
1%
12
#380
0%
02
#381
b10111101 \
b10111010 D
1%
12
#382
0%
02
#383
b10111110 \
b10111011 D
1%
12
#384
0%
02
#385
b10111111 \
b10111100 D
1%
12
#386
0%
02
#387
b11000000 \
b10111101 D
1%
12
#388
0%
02
#389
b11000001 \
b10111110 D
1%
12
#390
0%
02
#391
b11000010 \
b10111111 D
1%
12
#392
0%
02
#393
b11000011 \
b11000000 D
1%
12
#394
0%
02
#395
b11000100 \
b11000001 D
1%
12
#396
0%
02
#397
b11000101 \
b11000010 D
1%
12
#398
0%
02
#399
b11000110 \
b11000011 D
1%
12
#400
0%
02
#401
b11000111 \
b11000100 D
1%
12
#402
0%
02
#403
b11001000 \
b11000101 D
1%
12
#404
0%
02
#405
b11001001 \
b11000110 D
1%
12
#406
0%
02
#407
b11001010 \
b11000111 D
1%
12
#408
0%
02
#409
b11001011 \
b11001000 D
1%
12
#410
0%
02
#411
b11001100 \
b11001001 D
1%
12
#412
0%
02
#413
b11001101 \
b11001010 D
1%
12
#414
0%
02
#415
b11001110 \
b11001011 D
1%
12
#416
0%
02
#417
b11001111 \
b11001100 D
1%
12
#418
0%
02
#419
b11010000 \
b11001101 D
1%
12
#420
0%
02
#421
b11010001 \
b11001110 D
1%
12
#422
0%
02
#423
b11010010 \
b11001111 D
1%
12
#424
0%
02
#425
b11010011 \
b11010000 D
1%
12
#426
0%
02
#427
b11010100 \
b11010001 D
1%
12
#428
0%
02
#429
b11010101 \
b11010010 D
1%
12
#430
0%
02
#431
b11010110 \
b11010011 D
1%
12
#432
0%
02
#433
b11010111 \
b11010100 D
1%
12
#434
0%
02
#435
b11011000 \
b11010101 D
1%
12
#436
0%
02
#437
b11011001 \
b11010110 D
1%
12
#438
0%
02
#439
b11011010 \
b11010111 D
1%
12
#440
0%
02
#441
b11011011 \
b11011000 D
1%
12
#442
0%
02
#443
b11011100 \
b11011001 D
1%
12
#444
0%
02
#445
b11011101 \
b11011010 D
1%
12
#446
0%
02
#447
b11011110 \
b11011011 D
1%
12
#448
0%
02
#449
b11011111 \
b11011100 D
1%
12
#450
0%
02
#451
b11100000 \
b11011101 D
1%
12
#452
0%
02
#453
b11100001 \
b11011110 D
1%
12
#454
0%
02
#455
b11100010 \
b11011111 D
1%
12
#456
0%
02
#457
b11100011 \
b11100000 D
1%
12
#458
0%
02
#459
b11100100 \
b11100001 D
1%
12
#460
0%
02
